Metadata-Version: 1.0
Name: tia-distributions
Version: 0.1
Summary: Gaussian and Binomial distributions
Home-page: UNKNOWN
Author: Iddi Abdul Aziz
Author-email: iddiabdulaziz1@gmail.com
License: UNKNOWN
Platform: UNKNOWN
